postman_sync/__init__.py
postman_sync/endpoint_transfer.py
postman_sync/helper_functions.py
postman_sync/main_script.py
tests/__init__.py
tests/test_endpoint_transfer.py
tests/test_helper_functions.py
tests/test_main_script.py
postman_sync-0.1.2.dist-info/METADATA
postman_sync-0.1.2.dist-info/WHEEL
postman_sync-0.1.2.dist-info/entry_points.txt
postman_sync-0.1.2.dist-info/top_level.txt
postman_sync-0.1.2.dist-info/RECORD
