Metadata-Version: 2.1
Name: postman_sync
Version: 0.1.2
Summary: A tool to synchronize Postman collections with Swagger (OpenAPI) specifications
Home-page: https://github.com/BlazinArtemis/postman-swagger-automatic-sync
Author: Oluwaseyi Ajadi
Author-email: oluwaseyinexus137@gmail.com
Classifier: Programming Language :: Python :: 3
Classifier: License :: OSI Approved :: MIT License
Classifier: Operating System :: OS Independent
Requires-Python: >=3.6
Requires-Dist: requests
Requires-Dist: argparse
